Metadata-Version: 1.1
Name: cmsplugin-ss-icon
Version: 0.1.0b1
Summary: Add support for font awesome icons to django cms
Home-page: https://github.com/alexjbartlett/djangocms-ss-icon
Author: Alex J Bartlett
Author-email: alex@sourceshaper.com
License: MIT
Keywords: djangocms fontawesome
Platform: UNKNOWN
Classifier: Development Status :: 4 - Beta
Classifier: Intended Audience :: Developers
Classifier: Topic :: Software Development :: Build Tools
Classifier: License :: OSI Approved :: MIT License
Classifier: Programming Language :: Python :: 2
Classifier: Programming Language :: Python :: 2.7
Classifier: Programming Language :: Python :: 3
Classifier: Programming Language :: Python :: 3.3
Classifier: Programming Language :: Python :: 3.4
Classifier: Programming Language :: Python :: 3.5
